wav_finder/__init__.py
wav_finder/cli.py
wav_finder/finder.py
wav_finder-0.1.0.dist-info/licenses/LICENSE
wav_finder-0.1.0.dist-info/METADATA
wav_finder-0.1.0.dist-info/WHEEL
wav_finder-0.1.0.dist-info/entry_points.txt
wav_finder-0.1.0.dist-info/top_level.txt
wav_finder-0.1.0.dist-info/RECORD
