Metadata-Version: 2.4
Name: wav-finder
Version: 0.1.0
Summary: A tool to find WAV files from a given URL or path
Home-page: https://github.com/yourusername/wav-finder
Author: Your Name
Author-email: Your Name <your.email@example.com>
License: MIT
Project-URL: Homepage, https://github.com/yourusername/wav-finder
Project-URL: Repository, https://github.com/yourusername/wav-finder
Classifier: Development Status :: 3 - Alpha
Classifier: Intended Audience :: Developers
Classifier: License :: OSI Approved :: MIT License
Classifier: Operating System :: OS Independent
Classifier: Programming Language :: Python :: 3
Classifier: Programming Language :: Python :: 3.7
Classifier: Programming Language :: Python :: 3.8
Classifier: Programming Language :: Python :: 3.9
Classifier: Programming Language :: Python :: 3.10
Classifier: Programming Language :: Python :: 3.11
Requires-Python: >=3.7
License-File: LICENSE
Requires-Dist: requests>=2.25.0
Requires-Dist: beautifulsoup4>=4.9.0
Requires-Dist: urllib3>=1.26.0
Dynamic: author
Dynamic: home-page
Dynamic: license-file
Dynamic: requires-python
